socketserver.py
builtins.py
reprlib.py
queue.py
copyreg.py
html/entities.py
html/parser.py
html/__init__.py
xmlrpc/client.py
xmlrpc/__init__.py
http/cookiejar.py
http/client.py
http/server.py
http/cookies.py
http/__init__.py
pies2overrides-2.6.7.dist-info/top_level.txt
pies2overrides-2.6.7.dist-info/METADATA
pies2overrides-2.6.7.dist-info/RECORD
pies2overrides-2.6.7.dist-info/DESCRIPTION.rst
pies2overrides-2.6.7.dist-info/metadata.json
pies2overrides-2.6.7.dist-info/WHEEL
