Metadata-Version: 2.0
Name: pies2overrides
Version: 2.6.7
Summary: Defines override classes that should be included with pies only if running on Python2.
Home-page: https://github.com/timothycrosley/pies
Author: Timothy Crosley
Author-email: timothy.crosley@gmail.com
License: MIT
Download-URL: https://github.com/timothycrosley/pies/blob/master/pies2overrides/dist/pies2overrides-2.6.7.tar.gz?raw=true
Platform: UNKNOWN
Requires: ipaddress
Requires-Dist: ipaddress
Requires-Dist: ordereddict; python_version=="2.6"
Requires-Dist: argparse; python_version=="2.6"
